{
  "fetchTime": "2026-07-01T19:46:58.177138+08:00",
  "error": null,
  "fuels": [
    {
      "name": "燃氣",
      "mw": 1571.8
    },
    {
      "name": "民營燃氣",
      "mw": 600.5
    },
    {
      "name": "燃煤",
      "mw": 745.3
    },
    {
      "name": "民營燃煤",
      "mw": 215.2
    },
    {
      "name": "汽電共生",
      "mw": 206.1
    },
    {
      "name": "重油",
      "mw": 39.4
    },
    {
      "name": "風力",
      "mw": 12.9
    },
    {
      "name": "水力",
      "mw": 137.8
    },
    {
      "name": "儲能",
      "mw": 133.3
    },
    {
      "name": "其它再生能源",
      "mw": 4.1
    }
  ],
  "regions": {
    "北區": 1539.9,
    "中區": 879.9,
    "南區": 1063.3,
    "東區": 183.3
  },
  "load": 3666.4,
  "capacity": 4800.7,
  "utilRate": 76.4,
  "spareRate": 30.9,
  "updateTime": "115.07.01(三)19:40更新"
}