{
  "fetchTime": "2026-06-01T06:30:02.385533+08:00",
  "error": null,
  "fuels": [
    {
      "name": "燃氣",
      "mw": 1081.2
    },
    {
      "name": "民營燃氣",
      "mw": 261.3
    },
    {
      "name": "燃煤",
      "mw": 589.6
    },
    {
      "name": "民營燃煤",
      "mw": 210.1
    },
    {
      "name": "汽電共生",
      "mw": 103.5
    },
    {
      "name": "重油",
      "mw": 31.7
    },
    {
      "name": "太陽能",
      "mw": 82.8
    },
    {
      "name": "風力",
      "mw": 230.2
    },
    {
      "name": "水力",
      "mw": 27.8
    },
    {
      "name": "其它再生能源",
      "mw": 4.3
    }
  ],
  "regions": {
    "北區": 1061.9,
    "中區": 606.8,
    "南區": 733.2,
    "東區": 126.4
  },
  "load": 2528.4,
  "capacity": 4564.4,
  "utilRate": 55.4,
  "spareRate": 80.5,
  "updateTime": "115.06.01(一)06:20更新"
}