{
  "fetchTime": "2026-07-14T05:05:44.860902+08:00",
  "error": null,
  "fuels": [
    {
      "name": "燃氣",
      "mw": 1453.4
    },
    {
      "name": "民營燃氣",
      "mw": 291.5
    },
    {
      "name": "燃煤",
      "mw": 673.1
    },
    {
      "name": "民營燃煤",
      "mw": 213.0
    },
    {
      "name": "汽電共生",
      "mw": 92.0
    },
    {
      "name": "重油",
      "mw": 33.6
    },
    {
      "name": "太陽能",
      "mw": 0.3
    },
    {
      "name": "風力",
      "mw": 124.3
    },
    {
      "name": "水力",
      "mw": 50.8
    },
    {
      "name": "其它再生能源",
      "mw": 3.6
    }
  ],
  "regions": {
    "北區": 1177.3,
    "中區": 672.8,
    "南區": 812.9,
    "東區": 140.2
  },
  "load": 2803.2,
  "capacity": 4819.0,
  "utilRate": 58.2,
  "spareRate": 71.9,
  "updateTime": "115.07.14(二)05:00更新"
}