{
  "fetchTime": "2026-04-17T16:01:36.089694+08:00",
  "error": null,
  "fuels": [
    {
      "name": "燃氣",
      "mw": 1350.7
    },
    {
      "name": "民營燃氣",
      "mw": 547.1
    },
    {
      "name": "燃煤",
      "mw": 821.4
    },
    {
      "name": "民營燃煤",
      "mw": 60.0
    },
    {
      "name": "汽電共生",
      "mw": 170.6
    },
    {
      "name": "重油",
      "mw": 33.2
    },
    {
      "name": "太陽能",
      "mw": 355.8
    },
    {
      "name": "風力",
      "mw": 10.7
    },
    {
      "name": "水力",
      "mw": 30.3
    },
    {
      "name": "儲能",
      "mw": 83.0
    },
    {
      "name": "其它再生能源",
      "mw": 0.3
    }
  ],
  "regions": {
    "北區": 1462.3,
    "中區": 835.6,
    "南區": 1009.7,
    "東區": 174.1
  },
  "load": 3481.7,
  "capacity": 4403.0,
  "utilRate": 79.1,
  "spareRate": 26.5,
  "updateTime": "115.04.17(五)15:50更新"
}