{
  "fetchTime": "2026-06-24T23:13:31.593420+08:00",
  "error": null,
  "fuels": [
    {
      "name": "燃氣",
      "mw": 1695.4
    },
    {
      "name": "民營燃氣",
      "mw": 479.3
    },
    {
      "name": "燃煤",
      "mw": 649.9
    },
    {
      "name": "民營燃煤",
      "mw": 214.7
    },
    {
      "name": "汽電共生",
      "mw": 189.7
    },
    {
      "name": "重油",
      "mw": 35.4
    },
    {
      "name": "風力",
      "mw": 19.9
    },
    {
      "name": "水力",
      "mw": 121.9
    },
    {
      "name": "儲能",
      "mw": 51.6
    },
    {
      "name": "其它再生能源",
      "mw": 3.9
    }
  ],
  "regions": {
    "北區": 1453.2,
    "中區": 830.4,
    "南區": 1003.4,
    "東區": 173.0
  },
  "load": 3459.9,
  "capacity": 5025.3,
  "utilRate": 68.8,
  "spareRate": 45.2,
  "updateTime": "115.06.24(三)23:10更新"
}