{
  "fetchTime": "2026-06-07T05:59:03.310198+08:00",
  "error": null,
  "fuels": [
    {
      "name": "燃氣",
      "mw": 1232.9
    },
    {
      "name": "民營燃氣",
      "mw": 235.1
    },
    {
      "name": "燃煤",
      "mw": 575.0
    },
    {
      "name": "民營燃煤",
      "mw": 210.1
    },
    {
      "name": "汽電共生",
      "mw": 89.7
    },
    {
      "name": "重油",
      "mw": 33.0
    },
    {
      "name": "太陽能",
      "mw": 31.5
    },
    {
      "name": "風力",
      "mw": 159.5
    },
    {
      "name": "水力",
      "mw": 39.7
    },
    {
      "name": "其它再生能源",
      "mw": 4.0
    }
  ],
  "regions": {
    "北區": 1074.4,
    "中區": 613.9,
    "南區": 741.8,
    "東區": 127.9
  },
  "load": 2558.0,
  "capacity": 3630.8,
  "utilRate": 70.5,
  "spareRate": 41.9,
  "updateTime": "115.06.07(日)05:50更新"
}